setup.py
ptf_optimize/__init__.py
ptf_optimize/portfolio_optimize.py
ptf_optimize.egg-info/PKG-INFO
ptf_optimize.egg-info/SOURCES.txt
ptf_optimize.egg-info/dependency_links.txt
ptf_optimize.egg-info/not-zip-safe
ptf_optimize.egg-info/top_level.txt