Metadata-Version: 1.2
Name: ptf-optimize
Version: 0.0.5
Summary: get optimal portfolio
Home-page: https://github.com/JPL13
Author: Juan Piao
Author-email: juanpiao13@gmail.com
License: UNKNOWN
Platform: UNKNOWN
Classifier: Programming Language :: Python :: 3
Classifier: License :: OSI Approved :: MIT License
Classifier: Operating System :: OS Independent
Requires-Python: >=3.6
